pyh2.py
PyH2-0.1.1.dist-info/DESCRIPTION.rst
PyH2-0.1.1.dist-info/METADATA
PyH2-0.1.1.dist-info/RECORD
PyH2-0.1.1.dist-info/WHEEL
PyH2-0.1.1.dist-info/metadata.json
PyH2-0.1.1.dist-info/top_level.txt
