Metadata-Version: 2.0
Name: PyH2
Version: 0.1.1
Summary: A powerful python module to generate web content
Home-page: https://github.com/pypykim/pyh2
Author: Emmanuel Turlay/Kim Kong
Author-email: turlay@cern.ch/kongqingzhang@gmail.com
License: UNKNOWN
Platform: UNKNOWN
